crackeduuid/__init__.py
crackeduuid/cli.py
crackeduuid/uuid_fetcher.py
crackeduuid-0.1.dist-info/METADATA
crackeduuid-0.1.dist-info/WHEEL
crackeduuid-0.1.dist-info/entry_points.txt
crackeduuid-0.1.dist-info/top_level.txt
crackeduuid-0.1.dist-info/RECORD
